Metadata-Version: 2.4
Name: raillabel
Version: 4.2.0
Summary: A devkit for working with recorded and annotated train ride data from Deutsche Bahn.
Author: DB InfraGO AG
License: Apache-2.0
Project-URL: Homepage, https://github.com/DSD-DBS/raillabel
Project-URL: Documentation, https://dsd-dbs.github.io/raillabel
Platform: any
Classifier: Development Status :: 1 - Planning
Classifier: License :: OSI Approved :: Apache Software License
Classifier: Natural Language :: English
Classifier: Operating System :: OS Independent
Classifier: Programming Language :: Python :: 3 :: Only
Classifier: Programming Language :: Python :: 3.8
Classifier: Programming Language :: Python :: 3.9
Classifier: Programming Language :: Python :: 3.10
Classifier: Programming Language :: Python :: 3.11
Classifier: Programming Language :: Python :: 3.12
Classifier: Programming Language :: Python :: 3.13
Requires-Python: <3.14,>=3.8
License-File: LICENSE
Requires-Dist: pydantic<3.0.0
Requires-Dist: eval-type-backport==0.2.0
Provides-Extra: docs
Requires-Dist: furo; extra == "docs"
Requires-Dist: sphinx; extra == "docs"
Requires-Dist: sphinx-copybutton; extra == "docs"
Requires-Dist: tomli; python_version < "3.14" and extra == "docs"
Provides-Extra: test
Requires-Dist: pytest; extra == "test"
Requires-Dist: pytest-cov; extra == "test"
Requires-Dist: json5; extra == "test"
Dynamic: license-file
